Metadata-Version: 1.0
Name: common-distributions
Version: 0.1
Summary: Gaussian distributions
Home-page: UNKNOWN
Author: Chris Wang
Author-email: chris.wang92688@gmail.com
License: UNKNOWN
Platform: UNKNOWN
